MANIFEST.in
setup.py
django_simple_helpdesk.egg-info/PKG-INFO
django_simple_helpdesk.egg-info/SOURCES.txt
django_simple_helpdesk.egg-info/dependency_links.txt
django_simple_helpdesk.egg-info/requires.txt
django_simple_helpdesk.egg-info/top_level.txt
helpdesk/__init__.py
helpdesk/admin.py
helpdesk/forms.py
helpdesk/models.py
helpdesk/signals.py
helpdesk/tests.py
helpdesk/urls.py
helpdesk/utils.py
helpdesk/views.py
helpdesk/management/__init__.py
helpdesk/management/commands/__init__.py
helpdesk/management/commands/check_mail.py
helpdesk/management/commands/init_helpdesk.py
helpdesk/migrations/0001_initial.py
helpdesk/migrations/__init__.py
helpdesk/static/helpdesk/css/custom.css
helpdesk/static/helpdesk/css/jquery.dropdown.css
helpdesk/static/helpdesk/css/material-wfont.css
helpdesk/static/helpdesk/css/material-wfont.css.map
helpdesk/static/helpdesk/css/material-wfont.min.css
helpdesk/static/helpdesk/css/material-wfont.min.css.map
helpdesk/static/helpdesk/css/material.css
helpdesk/static/helpdesk/css/material.css.map
helpdesk/static/helpdesk/css/material.min.css
helpdesk/static/helpdesk/css/material.min.css.map
helpdesk/static/helpdesk/css/ripples.css
helpdesk/static/helpdesk/css/ripples.css.map
helpdesk/static/helpdesk/css/ripples.min.css
helpdesk/static/helpdesk/css/ripples.min.css.map
helpdesk/static/helpdesk/fonts/LICENSE.txt
helpdesk/static/helpdesk/fonts/Material-Design-Icons.eot
helpdesk/static/helpdesk/fonts/Material-Design-Icons.svg
helpdesk/static/helpdesk/fonts/Material-Design-Icons.ttf
helpdesk/static/helpdesk/fonts/Material-Design-Icons.woff
helpdesk/static/helpdesk/js/custom.js
helpdesk/static/helpdesk/js/jquery.dropdown.js
helpdesk/static/helpdesk/js/material.js
helpdesk/static/helpdesk/js/material.min.js
helpdesk/static/helpdesk/js/material.min.js.map
helpdesk/static/helpdesk/js/ripples.js
helpdesk/static/helpdesk/js/ripples.min.js
helpdesk/static/helpdesk/js/ripples.min.js.map
helpdesk/static/helpdesk/js/security.js
helpdesk/static/helpdesk/js/security.js.map
helpdesk/templates/test.html
helpdesk/templates/helpdesk/answer_added.html
helpdesk/templates/helpdesk/base.html
helpdesk/templates/helpdesk/comment.html
helpdesk/templates/helpdesk/comment_added.html
