Metadata-Version: 1.0
Name: django-simple-helpdesk
Version: 0.7.2
Summary: Simple HelpDesk for Django
Home-page: https://github.com/ookami-kb/django-simple-helpdesk
Author: Kirill Bubochkin
Author-email: ookami.kb@gmail.com
License: UNKNOWN
Platform: UNKNOWN
